dict_plus/__init__.py
dict_plus/etypes.py
dict_plus/exceptions.py
dict_plus/funcs.py
dict_plus/iterable.py
dict_plus/dicts/__init__.py
dict_plus/dicts/dictlist.py
dict_plus/dicts/dictplus.py
dict_plus/dicts/hooked.py
dict_plus/dicts/insensitive.py
dict_plus/dicts/ordered.py
dict_plus/elements/__init__.py
dict_plus/elements/element.py
dict_plus/indexes/__init__.py
dict_plus/indexes/index.py
dict_plus/indexes/ordered.py
dict_plus/lists/__init__.py
dict_plus/lists/listdict.py
dict_plus/lists/listplus.py
dict_plus/utils/__init__.py
dict_plus/utils/simpleflatten.py
dict_plus-0.3.6.dist-info/LICENSE
dict_plus-0.3.6.dist-info/METADATA
dict_plus-0.3.6.dist-info/WHEEL
dict_plus-0.3.6.dist-info/top_level.txt
dict_plus-0.3.6.dist-info/RECORD
