Metadata-Version: 2.1
Name: dict-plus
Version: 0.3.6
Summary: Extended Dictionary Package
Home-page: UNKNOWN
Author: Spencer Hanson
Author-email: spencerhanson3141@gmail.com
License: UNKNOWN
Keywords: list,utilities,dictionary
Platform: UNKNOWN
License-File: LICENSE
